{"dependencies":[{"name":"/Users/baidu/work/workspace/javascript/github/mark/package.json","includedInParent":true,"mtime":1519466866000},{"name":"/Users/baidu/work/workspace/javascript/github/mark/.babelrc","includedInParent":true,"mtime":1519374260000},{"name":"/Users/baidu/work/workspace/javascript/github/mark/node_modules/moment/package.json","includedInParent":true,"mtime":1519450795000},{"name":"../utils/abs-floor","loc":{"line":1,"column":21}}],"generated":{"js":"'use strict';\n\nObject.defineProperty(exports, \"__esModule\", {\n    value: true\n});\nexports.toISOString = toISOString;\n\nvar _absFloor = require('../utils/abs-floor');\n\nvar _absFloor2 = _interopRequireDefault(_absFloor);\n\nfunction _interopRequireDefault(obj) { return obj && obj.__esModule ? obj : { default: obj }; }\n\nvar abs = Math.abs;\n\nfunction sign(x) {\n    return (x > 0) - (x < 0) || +x;\n}\n\nfunction toISOString() {\n    // for ISO strings we do not use the normal bubbling rules:\n    //  * milliseconds bubble up until they become hours\n    //  * days do not bubble at all\n    //  * months bubble up until they become years\n    // This is because there is no context-free conversion between hours and days\n    // (think of clock changes)\n    // and also not between days and months (28-31 days per month)\n    if (!this.isValid()) {\n        return this.localeData().invalidDate();\n    }\n\n    var seconds = abs(this._milliseconds) / 1000;\n    var days = abs(this._days);\n    var months = abs(this._months);\n    var minutes, hours, years;\n\n    // 3600 seconds -> 60 minutes -> 1 hour\n    minutes = (0, _absFloor2.default)(seconds / 60);\n    hours = (0, _absFloor2.default)(minutes / 60);\n    seconds %= 60;\n    minutes %= 60;\n\n    // 12 months -> 1 year\n    years = (0, _absFloor2.default)(months / 12);\n    months %= 12;\n\n    // inspired by https://github.com/dordille/moment-isoduration/blob/master/moment.isoduration.js\n    var Y = years;\n    var M = months;\n    var D = days;\n    var h = hours;\n    var m = minutes;\n    var s = seconds ? seconds.toFixed(3).replace(/\\.?0+$/, '') : '';\n    var total = this.asSeconds();\n\n    if (!total) {\n        // this is the same as C#'s (Noda) and python (isodate)...\n        // but not other JS (goog.date)\n        return 'P0D';\n    }\n\n    var totalSign = total < 0 ? '-' : '';\n    var ymSign = sign(this._months) !== sign(total) ? '-' : '';\n    var daysSign = sign(this._days) !== sign(total) ? '-' : '';\n    var hmsSign = sign(this._milliseconds) !== sign(total) ? '-' : '';\n\n    return totalSign + 'P' + (Y ? ymSign + Y + 'Y' : '') + (M ? ymSign + M + 'M' : '') + (D ? daysSign + D + 'D' : '') + (h || m || s ? 'T' : '') + (h ? hmsSign + h + 'H' : '') + (m ? hmsSign + m + 'M' : '') + (s ? hmsSign + s + 'S' : '');\n}","map":{"mappings":[{"name":"toISOString","generated":{"line":6,"column":8},"source":"../node_modules/moment/src/lib/duration/iso-string.js","original":{"line":8,"column":16}},{"name":"toISOString","generated":{"line":6,"column":22},"source":"../node_modules/moment/src/lib/duration/iso-string.js","original":{"line":8,"column":16}},{"generated":{"line":8,"column":0},"source":"../node_modules/moment/src/lib/duration/iso-string.js","original":{"line":1,"column":0}},{"generated":{"line":14,"column":0},"source":"../node_modules/moment/src/lib/duration/iso-string.js","original":{"line":2,"column":0}},{"name":"abs","generated":{"line":14,"column":4},"source":"../node_modules/moment/src/lib/duration/iso-string.js","original":{"line":2,"column":4}},{"name":"Math","generated":{"line":14,"column":10},"source":"../node_modules/moment/src/lib/duration/iso-string.js","original":{"line":2,"column":10}},{"name":"abs","generated":{"line":14,"column":15},"source":"../node_modules/moment/src/lib/duration/iso-string.js","original":{"line":2,"column":15}},{"generated":{"line":14,"column":18},"source":"../node_modules/moment/src/lib/duration/iso-string.js","original":{"line":2,"column":0}},{"generated":{"line":16,"column":0},"source":"../node_modules/moment/src/lib/duration/iso-string.js","original":{"line":4,"column":0}},{"name":"sign","generated":{"line":16,"column":9},"source":"../node_modules/moment/src/lib/duration/iso-string.js","original":{"line":4,"column":9}},{"generated":{"line":16,"column":13},"source":"../node_modules/moment/src/lib/duration/iso-string.js","original":{"line":4,"column":0}},{"name":"x","generated":{"line":16,"column":14},"source":"../node_modules/moment/src/lib/duration/iso-string.js","original":{"line":4,"column":14}},{"generated":{"line":16,"column":15},"source":"../node_modules/moment/src/lib/duration/iso-string.js","original":{"line":4,"column":0}},{"generated":{"line":16,"column":17},"source":"../node_modules/moment/src/lib/duration/iso-string.js","original":{"line":4,"column":17}},{"generated":{"line":17,"column":0},"source":"../node_modules/moment/src/lib/duration/iso-string.js","original":{"line":5,"column":4}},{"generated":{"line":17,"column":11},"source":"../node_modules/moment/src/lib/duration/iso-string.js","original":{"line":5,"column":12}},{"name":"x","generated":{"line":17,"column":12},"source":"../node_modules/moment/src/lib/duration/iso-string.js","original":{"line":5,"column":13}},{"generated":{"line":17,"column":16},"source":"../node_modules/moment/src/lib/duration/iso-string.js","original":{"line":5,"column":17}},{"generated":{"line":17,"column":17},"source":"../node_modules/moment/src/lib/duration/iso-string.js","original":{"line":5,"column":12}},{"name":"x","generated":{"line":17,"column":22},"source":"../node_modules/moment/src/lib/duration/iso-string.js","original":{"line":5,"column":23}},{"generated":{"line":17,"column":26},"source":"../node_modules/moment/src/lib/duration/iso-string.js","original":{"line":5,"column":27}},{"generated":{"line":17,"column":27},"source":"../node_modules/moment/src/lib/duration/iso-string.js","original":{"line":5,"column":12}},{"generated":{"line":17,"column":28},"source":"../node_modules/moment/src/lib/duration/iso-string.js","original":{"line":5,"column":11}},{"generated":{"line":17,"column":32},"source":"../node_modules/moment/src/lib/duration/iso-string.js","original":{"line":5,"column":34}},{"name":"x","generated":{"line":17,"column":33},"source":"../node_modules/moment/src/lib/duration/iso-string.js","original":{"line":5,"column":35}},{"generated":{"line":17,"column":34},"source":"../node_modules/moment/src/lib/duration/iso-string.js","original":{"line":5,"column":4}},{"generated":{"line":18,"column":0},"source":"../node_modules/moment/src/lib/duration/iso-string.js","original":{"line":6,"column":1}},{"generated":{"line":20,"column":0},"source":"../node_modules/moment/src/lib/duration/iso-string.js","original":{"line":8,"column":7}},{"name":"toISOString","generated":{"line":20,"column":9},"source":"../node_modules/moment/src/lib/duration/iso-string.js","original":{"line":8,"column":16}},{"generated":{"line":20,"column":20},"source":"../node_modules/moment/src/lib/duration/iso-string.js","original":{"line":8,"column":7}},{"generated":{"line":20,"column":23},"source":"../node_modules/moment/src/lib/duration/iso-string.js","original":{"line":8,"column":30}},{"generated":{"line":21,"column":0},"source":"../node_modules/moment/src/lib/duration/iso-string.js","original":{"line":9,"column":4}},{"generated":{"line":22,"column":0},"source":"../node_modules/moment/src/lib/duration/iso-string.js","original":{"line":10,"column":4}},{"generated":{"line":23,"column":0},"source":"../node_modules/moment/src/lib/duration/iso-string.js","original":{"line":11,"column":4}},{"generated":{"line":24,"column":0},"source":"../node_modules/moment/src/lib/duration/iso-string.js","original":{"line":12,"column":4}},{"generated":{"line":25,"column":0},"source":"../node_modules/moment/src/lib/duration/iso-string.js","original":{"line":13,"column":4}},{"generated":{"line":26,"column":0},"source":"../node_modules/moment/src/lib/duration/iso-string.js","original":{"line":14,"column":4}},{"generated":{"line":27,"column":0},"source":"../node_modules/moment/src/lib/duration/iso-string.js","original":{"line":15,"column":4}},{"generated":{"line":28,"column":0},"source":"../node_modules/moment/src/lib/duration/iso-string.js","original":{"line":16,"column":4}},{"generated":{"line":28,"column":8},"source":"../node_modules/moment/src/lib/duration/iso-string.js","original":{"line":16,"column":8}},{"generated":{"line":28,"column":9},"source":"../node_modules/moment/src/lib/duration/iso-string.js","original":{"line":16,"column":9}},{"name":"isValid","generated":{"line":28,"column":14},"source":"../node_modules/moment/src/lib/duration/iso-string.js","original":{"line":16,"column":14}},{"generated":{"line":28,"column":21},"source":"../node_modules/moment/src/lib/duration/iso-string.js","original":{"line":16,"column":9}},{"generated":{"line":28,"column":23},"source":"../node_modules/moment/src/lib/duration/iso-string.js","original":{"line":16,"column":4}},{"generated":{"line":28,"column":25},"source":"../node_modules/moment/src/lib/duration/iso-string.js","original":{"line":16,"column":25}},{"generated":{"line":29,"column":0},"source":"../node_modules/moment/src/lib/duration/iso-string.js","original":{"line":17,"column":8}},{"generated":{"line":29,"column":15},"source":"../node_modules/moment/src/lib/duration/iso-string.js","original":{"line":17,"column":15}},{"name":"localeData","generated":{"line":29,"column":20},"source":"../node_modules/moment/src/lib/duration/iso-string.js","original":{"line":17,"column":20}},{"generated":{"line":29,"column":30},"source":"../node_modules/moment/src/lib/duration/iso-string.js","original":{"line":17,"column":15}},{"name":"invalidDate","generated":{"line":29,"column":33},"source":"../node_modules/moment/src/lib/duration/iso-string.js","original":{"line":17,"column":33}},{"generated":{"line":29,"column":44},"source":"../node_modules/moment/src/lib/duration/iso-string.js","original":{"line":17,"column":15}},{"generated":{"line":29,"column":46},"source":"../node_modules/moment/src/lib/duration/iso-string.js","original":{"line":17,"column":8}},{"generated":{"line":30,"column":0},"source":"../node_modules/moment/src/lib/duration/iso-string.js","original":{"line":18,"column":5}},{"generated":{"line":32,"column":0},"source":"../node_modules/moment/src/lib/duration/iso-string.js","original":{"line":20,"column":4}},{"name":"seconds","generated":{"line":32,"column":8},"source":"../node_modules/moment/src/lib/duration/iso-string.js","original":{"line":20,"column":8}},{"name":"abs","generated":{"line":32,"column":18},"source":"../node_modules/moment/src/lib/duration/iso-string.js","original":{"line":20,"column":18}},{"generated":{"line":32,"column":22},"source":"../node_modules/moment/src/lib/duration/iso-string.js","original":{"line":20,"column":22}},{"name":"_milliseconds","generated":{"line":32,"column":27},"source":"../node_modules/moment/src/lib/duration/iso-string.js","original":{"line":20,"column":27}},{"generated":{"line":32,"column":40},"source":"../node_modules/moment/src/lib/duration/iso-string.js","original":{"line":20,"column":18}},{"generated":{"line":32,"column":44},"source":"../node_modules/moment/src/lib/duration/iso-string.js","original":{"line":20,"column":44}},{"generated":{"line":32,"column":48},"source":"../node_modules/moment/src/lib/duration/iso-string.js","original":{"line":20,"column":4}},{"generated":{"line":33,"column":0},"source":"../node_modules/moment/src/lib/duration/iso-string.js","original":{"line":21,"column":4}},{"name":"days","generated":{"line":33,"column":8},"source":"../node_modules/moment/src/lib/duration/iso-string.js","original":{"line":21,"column":8}},{"name":"abs","generated":{"line":33,"column":15},"source":"../node_modules/moment/src/lib/duration/iso-string.js","original":{"line":21,"column":23}},{"generated":{"line":33,"column":19},"source":"../node_modules/moment/src/lib/duration/iso-string.js","original":{"line":21,"column":27}},{"name":"_days","generated":{"line":33,"column":24},"source":"../node_modules/moment/src/lib/duration/iso-string.js","original":{"line":21,"column":32}},{"generated":{"line":33,"column":29},"source":"../node_modules/moment/src/lib/duration/iso-string.js","original":{"line":21,"column":23}},{"generated":{"line":33,"column":30},"source":"../node_modules/moment/src/lib/duration/iso-string.js","original":{"line":21,"column":4}},{"generated":{"line":34,"column":0},"source":"../node_modules/moment/src/lib/duration/iso-string.js","original":{"line":22,"column":4}},{"name":"months","generated":{"line":34,"column":8},"source":"../node_modules/moment/src/lib/duration/iso-string.js","original":{"line":22,"column":8}},{"name":"abs","generated":{"line":34,"column":17},"source":"../node_modules/moment/src/lib/duration/iso-string.js","original":{"line":22,"column":23}},{"generated":{"line":34,"column":21},"source":"../node_modules/moment/src/lib/duration/iso-string.js","original":{"line":22,"column":27}},{"name":"_months","generated":{"line":34,"column":26},"source":"../node_modules/moment/src/lib/duration/iso-string.js","original":{"line":22,"column":32}},{"generated":{"line":34,"column":33},"source":"../node_modules/moment/src/lib/duration/iso-string.js","original":{"line":22,"column":23}},{"generated":{"line":34,"column":34},"source":"../node_modules/moment/src/lib/duration/iso-string.js","original":{"line":22,"column":4}},{"generated":{"line":35,"column":0},"source":"../node_modules/moment/src/lib/duration/iso-string.js","original":{"line":23,"column":4}},{"name":"minutes","generated":{"line":35,"column":8},"source":"../node_modules/moment/src/lib/duration/iso-string.js","original":{"line":23,"column":8}},{"generated":{"line":35,"column":15},"source":"../node_modules/moment/src/lib/duration/iso-string.js","original":{"line":23,"column":4}},{"name":"hours","generated":{"line":35,"column":17},"source":"../node_modules/moment/src/lib/duration/iso-string.js","original":{"line":23,"column":17}},{"generated":{"line":35,"column":22},"source":"../node_modules/moment/src/lib/duration/iso-string.js","original":{"line":23,"column":4}},{"name":"years","generated":{"line":35,"column":24},"source":"../node_modules/moment/src/lib/duration/iso-string.js","original":{"line":23,"column":24}},{"generated":{"line":35,"column":29},"source":"../node_modules/moment/src/lib/duration/iso-string.js","original":{"line":23,"column":4}},{"generated":{"line":37,"column":0},"source":"../node_modules/moment/src/lib/duration/iso-string.js","original":{"line":25,"column":4}},{"name":"minutes","generated":{"line":38,"column":0},"source":"../node_modules/moment/src/lib/duration/iso-string.js","original":{"line":26,"column":4}},{"generated":{"line":38,"column":14},"source":"../node_modules/moment/src/lib/duration/iso-string.js","original":{"line":26,"column":24}},{"name":"seconds","generated":{"line":38,"column":38},"source":"../node_modules/moment/src/lib/duration/iso-string.js","original":{"line":26,"column":33}},{"generated":{"line":38,"column":48},"source":"../node_modules/moment/src/lib/duration/iso-string.js","original":{"line":26,"column":43}},{"generated":{"line":38,"column":50},"source":"../node_modules/moment/src/lib/duration/iso-string.js","original":{"line":26,"column":24}},{"generated":{"line":38,"column":51},"source":"../node_modules/moment/src/lib/duration/iso-string.js","original":{"line":26,"column":4}},{"name":"hours","generated":{"line":39,"column":0},"source":"../node_modules/moment/src/lib/duration/iso-string.js","original":{"line":27,"column":4}},{"generated":{"line":39,"column":12},"source":"../node_modules/moment/src/lib/duration/iso-string.js","original":{"line":27,"column":24}},{"name":"minutes","generated":{"line":39,"column":36},"source":"../node_modules/moment/src/lib/duration/iso-string.js","original":{"line":27,"column":33}},{"generated":{"line":39,"column":46},"source":"../node_modules/moment/src/lib/duration/iso-string.js","original":{"line":27,"column":43}},{"generated":{"line":39,"column":48},"source":"../node_modules/moment/src/lib/duration/iso-string.js","original":{"line":27,"column":24}},{"generated":{"line":39,"column":49},"source":"../node_modules/moment/src/lib/duration/iso-string.js","original":{"line":27,"column":4}},{"name":"seconds","generated":{"line":40,"column":0},"source":"../node_modules/moment/src/lib/duration/iso-string.js","original":{"line":28,"column":4}},{"generated":{"line":40,"column":15},"source":"../node_modules/moment/src/lib/duration/iso-string.js","original":{"line":28,"column":15}},{"generated":{"line":40,"column":17},"source":"../node_modules/moment/src/lib/duration/iso-string.js","original":{"line":28,"column":4}},{"name":"minutes","generated":{"line":41,"column":0},"source":"../node_modules/moment/src/lib/duration/iso-string.js","original":{"line":29,"column":4}},{"generated":{"line":41,"column":15},"source":"../node_modules/moment/src/lib/duration/iso-string.js","original":{"line":29,"column":15}},{"generated":{"line":41,"column":17},"source":"../node_modules/moment/src/lib/duration/iso-string.js","original":{"line":29,"column":4}},{"generated":{"line":43,"column":0},"source":"../node_modules/moment/src/lib/duration/iso-string.js","original":{"line":31,"column":4}},{"name":"years","generated":{"line":44,"column":0},"source":"../node_modules/moment/src/lib/duration/iso-string.js","original":{"line":32,"column":4}},{"generated":{"line":44,"column":12},"source":"../node_modules/moment/src/lib/duration/iso-string.js","original":{"line":32,"column":13}},{"name":"months","generated":{"line":44,"column":36},"source":"../node_modules/moment/src/lib/duration/iso-string.js","original":{"line":32,"column":22}},{"generated":{"line":44,"column":45},"source":"../node_modules/moment/src/lib/duration/iso-string.js","original":{"line":32,"column":31}},{"generated":{"line":44,"column":47},"source":"../node_modules/moment/src/lib/duration/iso-string.js","original":{"line":32,"column":13}},{"generated":{"line":44,"column":48},"source":"../node_modules/moment/src/lib/duration/iso-string.js","original":{"line":32,"column":4}},{"name":"months","generated":{"line":45,"column":0},"source":"../node_modules/moment/src/lib/duration/iso-string.js","original":{"line":33,"column":4}},{"generated":{"line":45,"column":14},"source":"../node_modules/moment/src/lib/duration/iso-string.js","original":{"line":33,"column":14}},{"generated":{"line":45,"column":16},"source":"../node_modules/moment/src/lib/duration/iso-string.js","original":{"line":33,"column":4}},{"generated":{"line":47,"column":0},"source":"../node_modules/moment/src/lib/duration/iso-string.js","original":{"line":36,"column":4}},{"generated":{"line":48,"column":0},"source":"../node_modules/moment/src/lib/duration/iso-string.js","original":{"line":37,"column":4}},{"name":"Y","generated":{"line":48,"column":8},"source":"../node_modules/moment/src/lib/duration/iso-string.js","original":{"line":37,"column":8}},{"name":"years","generated":{"line":48,"column":12},"source":"../node_modules/moment/src/lib/duration/iso-string.js","original":{"line":37,"column":12}},{"generated":{"line":48,"column":17},"source":"../node_modules/moment/src/lib/duration/iso-string.js","original":{"line":37,"column":4}},{"generated":{"line":49,"column":0},"source":"../node_modules/moment/src/lib/duration/iso-string.js","original":{"line":38,"column":4}},{"name":"M","generated":{"line":49,"column":8},"source":"../node_modules/moment/src/lib/duration/iso-string.js","original":{"line":38,"column":8}},{"name":"months","generated":{"line":49,"column":12},"source":"../node_modules/moment/src/lib/duration/iso-string.js","original":{"line":38,"column":12}},{"generated":{"line":49,"column":18},"source":"../node_modules/moment/src/lib/duration/iso-string.js","original":{"line":38,"column":4}},{"generated":{"line":50,"column":0},"source":"../node_modules/moment/src/lib/duration/iso-string.js","original":{"line":39,"column":4}},{"name":"D","generated":{"line":50,"column":8},"source":"../node_modules/moment/src/lib/duration/iso-string.js","original":{"line":39,"column":8}},{"name":"days","generated":{"line":50,"column":12},"source":"../node_modules/moment/src/lib/duration/iso-string.js","original":{"line":39,"column":12}},{"generated":{"line":50,"column":16},"source":"../node_modules/moment/src/lib/duration/iso-string.js","original":{"line":39,"column":4}},{"generated":{"line":51,"column":0},"source":"../node_modules/moment/src/lib/duration/iso-string.js","original":{"line":40,"column":4}},{"name":"h","generated":{"line":51,"column":8},"source":"../node_modules/moment/src/lib/duration/iso-string.js","original":{"line":40,"column":8}},{"name":"hours","generated":{"line":51,"column":12},"source":"../node_modules/moment/src/lib/duration/iso-string.js","original":{"line":40,"column":12}},{"generated":{"line":51,"column":17},"source":"../node_modules/moment/src/lib/duration/iso-string.js","original":{"line":40,"column":4}},{"generated":{"line":52,"column":0},"source":"../node_modules/moment/src/lib/duration/iso-string.js","original":{"line":41,"column":4}},{"name":"m","generated":{"line":52,"column":8},"source":"../node_modules/moment/src/lib/duration/iso-string.js","original":{"line":41,"column":8}},{"name":"minutes","generated":{"line":52,"column":12},"source":"../node_modules/moment/src/lib/duration/iso-string.js","original":{"line":41,"column":12}},{"generated":{"line":52,"column":19},"source":"../node_modules/moment/src/lib/duration/iso-string.js","original":{"line":41,"column":4}},{"generated":{"line":53,"column":0},"source":"../node_modules/moment/src/lib/duration/iso-string.js","original":{"line":42,"column":4}},{"name":"s","generated":{"line":53,"column":8},"source":"../node_modules/moment/src/lib/duration/iso-string.js","original":{"line":42,"column":8}},{"name":"seconds","generated":{"line":53,"column":12},"source":"../node_modules/moment/src/lib/duration/iso-string.js","original":{"line":42,"column":12}},{"name":"seconds","generated":{"line":53,"column":22},"source":"../node_modules/moment/src/lib/duration/iso-string.js","original":{"line":42,"column":22}},{"name":"toFixed","generated":{"line":53,"column":30},"source":"../node_modules/moment/src/lib/duration/iso-string.js","original":{"line":42,"column":30}},{"generated":{"line":53,"column":37},"source":"../node_modules/moment/src/lib/duration/iso-string.js","original":{"line":42,"column":22}},{"generated":{"line":53,"column":38},"source":"../node_modules/moment/src/lib/duration/iso-string.js","original":{"line":42,"column":38}},{"generated":{"line":53,"column":39},"source":"../node_modules/moment/src/lib/duration/iso-string.js","original":{"line":42,"column":22}},{"name":"replace","generated":{"line":53,"column":41},"source":"../node_modules/moment/src/lib/duration/iso-string.js","original":{"line":42,"column":41}},{"generated":{"line":53,"column":48},"source":"../node_modules/moment/src/lib/duration/iso-string.js","original":{"line":42,"column":22}},{"generated":{"line":53,"column":49},"source":"../node_modules/moment/src/lib/duration/iso-string.js","original":{"line":42,"column":49}},{"generated":{"line":53,"column":57},"source":"../node_modules/moment/src/lib/duration/iso-string.js","original":{"line":42,"column":22}},{"generated":{"line":53,"column":59},"source":"../node_modules/moment/src/lib/duration/iso-string.js","original":{"line":42,"column":59}},{"generated":{"line":53,"column":61},"source":"../node_modules/moment/src/lib/duration/iso-string.js","original":{"line":42,"column":22}},{"generated":{"line":53,"column":62},"source":"../node_modules/moment/src/lib/duration/iso-string.js","original":{"line":42,"column":12}},{"generated":{"line":53,"column":65},"source":"../node_modules/moment/src/lib/duration/iso-string.js","original":{"line":42,"column":65}},{"generated":{"line":53,"column":67},"source":"../node_modules/moment/src/lib/duration/iso-string.js","original":{"line":42,"column":4}},{"generated":{"line":54,"column":0},"source":"../node_modules/moment/src/lib/duration/iso-string.js","original":{"line":43,"column":4}},{"name":"total","generated":{"line":54,"column":8},"source":"../node_modules/moment/src/lib/duration/iso-string.js","original":{"line":43,"column":8}},{"generated":{"line":54,"column":16},"source":"../node_modules/moment/src/lib/duration/iso-string.js","original":{"line":43,"column":16}},{"name":"asSeconds","generated":{"line":54,"column":21},"source":"../node_modules/moment/src/lib/duration/iso-string.js","original":{"line":43,"column":21}},{"generated":{"line":54,"column":30},"source":"../node_modules/moment/src/lib/duration/iso-string.js","original":{"line":43,"column":16}},{"generated":{"line":54,"column":32},"source":"../node_modules/moment/src/lib/duration/iso-string.js","original":{"line":43,"column":4}},{"generated":{"line":56,"column":0},"source":"../node_modules/moment/src/lib/duration/iso-string.js","original":{"line":45,"column":4}},{"generated":{"line":56,"column":8},"source":"../node_modules/moment/src/lib/duration/iso-string.js","original":{"line":45,"column":8}},{"name":"total","generated":{"line":56,"column":9},"source":"../node_modules/moment/src/lib/duration/iso-string.js","original":{"line":45,"column":9}},{"generated":{"line":56,"column":14},"source":"../node_modules/moment/src/lib/duration/iso-string.js","original":{"line":45,"column":4}},{"generated":{"line":56,"column":16},"source":"../node_modules/moment/src/lib/duration/iso-string.js","original":{"line":45,"column":16}},{"generated":{"line":57,"column":0},"source":"../node_modules/moment/src/lib/duration/iso-string.js","original":{"line":46,"column":8}},{"generated":{"line":58,"column":0},"source":"../node_modules/moment/src/lib/duration/iso-string.js","original":{"line":47,"column":8}},{"generated":{"line":59,"column":0},"source":"../node_modules/moment/src/lib/duration/iso-string.js","original":{"line":48,"column":8}},{"generated":{"line":59,"column":15},"source":"../node_modules/moment/src/lib/duration/iso-string.js","original":{"line":48,"column":15}},{"generated":{"line":59,"column":20},"source":"../node_modules/moment/src/lib/duration/iso-string.js","original":{"line":48,"column":8}},{"generated":{"line":60,"column":0},"source":"../node_modules/moment/src/lib/duration/iso-string.js","original":{"line":49,"column":5}},{"generated":{"line":62,"column":0},"source":"../node_modules/moment/src/lib/duration/iso-string.js","original":{"line":51,"column":4}},{"name":"totalSign","generated":{"line":62,"column":8},"source":"../node_modules/moment/src/lib/duration/iso-string.js","original":{"line":51,"column":8}},{"name":"total","generated":{"line":62,"column":20},"source":"../node_modules/moment/src/lib/duration/iso-string.js","original":{"line":51,"column":20}},{"generated":{"line":62,"column":28},"source":"../node_modules/moment/src/lib/duration/iso-string.js","original":{"line":51,"column":28}},{"generated":{"line":62,"column":29},"source":"../node_modules/moment/src/lib/duration/iso-string.js","original":{"line":51,"column":20}},{"generated":{"line":62,"column":32},"source":"../node_modules/moment/src/lib/duration/iso-string.js","original":{"line":51,"column":32}},{"generated":{"line":62,"column":35},"source":"../node_modules/moment/src/lib/duration/iso-string.js","original":{"line":51,"column":20}},{"generated":{"line":62,"column":38},"source":"../node_modules/moment/src/lib/duration/iso-string.js","original":{"line":51,"column":38}},{"generated":{"line":62,"column":40},"source":"../node_modules/moment/src/lib/duration/iso-string.js","original":{"line":51,"column":4}},{"generated":{"line":63,"column":0},"source":"../node_modules/moment/src/lib/duration/iso-string.js","original":{"line":52,"column":4}},{"name":"ymSign","generated":{"line":63,"column":8},"source":"../node_modules/moment/src/lib/duration/iso-string.js","original":{"line":52,"column":8}},{"name":"sign","generated":{"line":63,"column":17},"source":"../node_modules/moment/src/lib/duration/iso-string.js","original":{"line":52,"column":17}},{"generated":{"line":63,"column":22},"source":"../node_modules/moment/src/lib/duration/iso-string.js","original":{"line":52,"column":22}},{"name":"_months","generated":{"line":63,"column":27},"source":"../node_modules/moment/src/lib/duration/iso-string.js","original":{"line":52,"column":27}},{"generated":{"line":63,"column":34},"source":"../node_modules/moment/src/lib/duration/iso-string.js","original":{"line":52,"column":17}},{"name":"sign","generated":{"line":63,"column":40},"source":"../node_modules/moment/src/lib/duration/iso-string.js","original":{"line":52,"column":40}},{"name":"total","generated":{"line":63,"column":45},"source":"../node_modules/moment/src/lib/duration/iso-string.js","original":{"line":52,"column":45}},{"generated":{"line":63,"column":50},"source":"../node_modules/moment/src/lib/duration/iso-string.js","original":{"line":52,"column":40}},{"generated":{"line":63,"column":51},"source":"../node_modules/moment/src/lib/duration/iso-string.js","original":{"line":52,"column":17}},{"generated":{"line":63,"column":54},"source":"../node_modules/moment/src/lib/duration/iso-string.js","original":{"line":52,"column":54}},{"generated":{"line":63,"column":57},"source":"../node_modules/moment/src/lib/duration/iso-string.js","original":{"line":52,"column":17}},{"generated":{"line":63,"column":60},"source":"../node_modules/moment/src/lib/duration/iso-string.js","original":{"line":52,"column":60}},{"generated":{"line":63,"column":62},"source":"../node_modules/moment/src/lib/duration/iso-string.js","original":{"line":52,"column":4}},{"generated":{"line":64,"column":0},"source":"../node_modules/moment/src/lib/duration/iso-string.js","original":{"line":53,"column":4}},{"name":"daysSign","generated":{"line":64,"column":8},"source":"../node_modules/moment/src/lib/duration/iso-string.js","original":{"line":53,"column":8}},{"name":"sign","generated":{"line":64,"column":19},"source":"../node_modules/moment/src/lib/duration/iso-string.js","original":{"line":53,"column":19}},{"generated":{"line":64,"column":24},"source":"../node_modules/moment/src/lib/duration/iso-string.js","original":{"line":53,"column":24}},{"name":"_days","generated":{"line":64,"column":29},"source":"../node_modules/moment/src/lib/duration/iso-string.js","original":{"line":53,"column":29}},{"generated":{"line":64,"column":34},"source":"../node_modules/moment/src/lib/duration/iso-string.js","original":{"line":53,"column":19}},{"name":"sign","generated":{"line":64,"column":40},"source":"../node_modules/moment/src/lib/duration/iso-string.js","original":{"line":53,"column":40}},{"name":"total","generated":{"line":64,"column":45},"source":"../node_modules/moment/src/lib/duration/iso-string.js","original":{"line":53,"column":45}},{"generated":{"line":64,"column":50},"source":"../node_modules/moment/src/lib/duration/iso-string.js","original":{"line":53,"column":40}},{"generated":{"line":64,"column":51},"source":"../node_modules/moment/src/lib/duration/iso-string.js","original":{"line":53,"column":19}},{"generated":{"line":64,"column":54},"source":"../node_modules/moment/src/lib/duration/iso-string.js","original":{"line":53,"column":54}},{"generated":{"line":64,"column":57},"source":"../node_modules/moment/src/lib/duration/iso-string.js","original":{"line":53,"column":19}},{"generated":{"line":64,"column":60},"source":"../node_modules/moment/src/lib/duration/iso-string.js","original":{"line":53,"column":60}},{"generated":{"line":64,"column":62},"source":"../node_modules/moment/src/lib/duration/iso-string.js","original":{"line":53,"column":4}},{"generated":{"line":65,"column":0},"source":"../node_modules/moment/src/lib/duration/iso-string.js","original":{"line":54,"column":4}},{"name":"hmsSign","generated":{"line":65,"column":8},"source":"../node_modules/moment/src/lib/duration/iso-string.js","original":{"line":54,"column":8}},{"name":"sign","generated":{"line":65,"column":18},"source":"../node_modules/moment/src/lib/duration/iso-string.js","original":{"line":54,"column":18}},{"generated":{"line":65,"column":23},"source":"../node_modules/moment/src/lib/duration/iso-string.js","original":{"line":54,"column":23}},{"name":"_milliseconds","generated":{"line":65,"column":28},"source":"../node_modules/moment/src/lib/duration/iso-string.js","original":{"line":54,"column":28}},{"generated":{"line":65,"column":41},"source":"../node_modules/moment/src/lib/duration/iso-string.js","original":{"line":54,"column":18}},{"name":"sign","generated":{"line":65,"column":47},"source":"../node_modules/moment/src/lib/duration/iso-string.js","original":{"line":54,"column":47}},{"name":"total","generated":{"line":65,"column":52},"source":"../node_modules/moment/src/lib/duration/iso-string.js","original":{"line":54,"column":52}},{"generated":{"line":65,"column":57},"source":"../node_modules/moment/src/lib/duration/iso-string.js","original":{"line":54,"column":47}},{"generated":{"line":65,"column":58},"source":"../node_modules/moment/src/lib/duration/iso-string.js","original":{"line":54,"column":18}},{"generated":{"line":65,"column":61},"source":"../node_modules/moment/src/lib/duration/iso-string.js","original":{"line":54,"column":61}},{"generated":{"line":65,"column":64},"source":"../node_modules/moment/src/lib/duration/iso-string.js","original":{"line":54,"column":18}},{"generated":{"line":65,"column":67},"source":"../node_modules/moment/src/lib/duration/iso-string.js","original":{"line":54,"column":67}},{"generated":{"line":65,"column":69},"source":"../node_modules/moment/src/lib/duration/iso-string.js","original":{"line":54,"column":4}},{"generated":{"line":67,"column":0},"source":"../node_modules/moment/src/lib/duration/iso-string.js","original":{"line":56,"column":4}},{"name":"totalSign","generated":{"line":67,"column":11},"source":"../node_modules/moment/src/lib/duration/iso-string.js","original":{"line":56,"column":11}},{"generated":{"line":67,"column":23},"source":"../node_modules/moment/src/lib/duration/iso-string.js","original":{"line":56,"column":23}},{"generated":{"line":67,"column":26},"source":"../node_modules/moment/src/lib/duration/iso-string.js","original":{"line":56,"column":11}},{"name":"Y","generated":{"line":67,"column":30},"source":"../node_modules/moment/src/lib/duration/iso-string.js","original":{"line":57,"column":9}},{"name":"ymSign","generated":{"line":67,"column":34},"source":"../node_modules/moment/src/lib/duration/iso-string.js","original":{"line":57,"column":13}},{"name":"Y","generated":{"line":67,"column":43},"source":"../node_modules/moment/src/lib/duration/iso-string.js","original":{"line":57,"column":22}},{"generated":{"line":67,"column":44},"source":"../node_modules/moment/src/lib/duration/iso-string.js","original":{"line":57,"column":13}},{"generated":{"line":67,"column":47},"source":"../node_modules/moment/src/lib/duration/iso-string.js","original":{"line":57,"column":26}},{"generated":{"line":67,"column":50},"source":"../node_modules/moment/src/lib/duration/iso-string.js","original":{"line":57,"column":9}},{"generated":{"line":67,"column":53},"source":"../node_modules/moment/src/lib/duration/iso-string.js","original":{"line":57,"column":32}},{"generated":{"line":67,"column":55},"source":"../node_modules/moment/src/lib/duration/iso-string.js","original":{"line":56,"column":11}},{"name":"M","generated":{"line":67,"column":60},"source":"../node_modules/moment/src/lib/duration/iso-string.js","original":{"line":58,"column":9}},{"name":"ymSign","generated":{"line":67,"column":64},"source":"../node_modules/moment/src/lib/duration/iso-string.js","original":{"line":58,"column":13}},{"name":"M","generated":{"line":67,"column":73},"source":"../node_modules/moment/src/lib/duration/iso-string.js","original":{"line":58,"column":22}},{"generated":{"line":67,"column":74},"source":"../node_modules/moment/src/lib/duration/iso-string.js","original":{"line":58,"column":13}},{"generated":{"line":67,"column":77},"source":"../node_modules/moment/src/lib/duration/iso-string.js","original":{"line":58,"column":26}},{"generated":{"line":67,"column":80},"source":"../node_modules/moment/src/lib/duration/iso-string.js","original":{"line":58,"column":9}},{"generated":{"line":67,"column":83},"source":"../node_modules/moment/src/lib/duration/iso-string.js","original":{"line":58,"column":32}},{"generated":{"line":67,"column":85},"source":"../node_modules/moment/src/lib/duration/iso-string.js","original":{"line":56,"column":11}},{"name":"D","generated":{"line":67,"column":90},"source":"../node_modules/moment/src/lib/duration/iso-string.js","original":{"line":59,"column":9}},{"name":"daysSign","generated":{"line":67,"column":94},"source":"../node_modules/moment/src/lib/duration/iso-string.js","original":{"line":59,"column":13}},{"name":"D","generated":{"line":67,"column":105},"source":"../node_modules/moment/src/lib/duration/iso-string.js","original":{"line":59,"column":24}},{"generated":{"line":67,"column":106},"source":"../node_modules/moment/src/lib/duration/iso-string.js","original":{"line":59,"column":13}},{"generated":{"line":67,"column":109},"source":"../node_modules/moment/src/lib/duration/iso-string.js","original":{"line":59,"column":28}},{"generated":{"line":67,"column":112},"source":"../node_modules/moment/src/lib/duration/iso-string.js","original":{"line":59,"column":9}},{"generated":{"line":67,"column":115},"source":"../node_modules/moment/src/lib/duration/iso-string.js","original":{"line":59,"column":34}},{"generated":{"line":67,"column":117},"source":"../node_modules/moment/src/lib/duration/iso-string.js","original":{"line":56,"column":11}},{"name":"h","generated":{"line":67,"column":122},"source":"../node_modules/moment/src/lib/duration/iso-string.js","original":{"line":60,"column":10}},{"name":"m","generated":{"line":67,"column":127},"source":"../node_modules/moment/src/lib/duration/iso-string.js","original":{"line":60,"column":15}},{"generated":{"line":67,"column":128},"source":"../node_modules/moment/src/lib/duration/iso-string.js","original":{"line":60,"column":10}},{"name":"s","generated":{"line":67,"column":132},"source":"../node_modules/moment/src/lib/duration/iso-string.js","original":{"line":60,"column":20}},{"generated":{"line":67,"column":133},"source":"../node_modules/moment/src/lib/duration/iso-string.js","original":{"line":60,"column":9}},{"generated":{"line":67,"column":136},"source":"../node_modules/moment/src/lib/duration/iso-string.js","original":{"line":60,"column":25}},{"generated":{"line":67,"column":139},"source":"../node_modules/moment/src/lib/duration/iso-string.js","original":{"line":60,"column":9}},{"generated":{"line":67,"column":142},"source":"../node_modules/moment/src/lib/duration/iso-string.js","original":{"line":60,"column":31}},{"generated":{"line":67,"column":144},"source":"../node_modules/moment/src/lib/duration/iso-string.js","original":{"line":56,"column":11}},{"name":"h","generated":{"line":67,"column":149},"source":"../node_modules/moment/src/lib/duration/iso-string.js","original":{"line":61,"column":9}},{"name":"hmsSign","generated":{"line":67,"column":153},"source":"../node_modules/moment/src/lib/duration/iso-string.js","original":{"line":61,"column":13}},{"name":"h","generated":{"line":67,"column":163},"source":"../node_modules/moment/src/lib/duration/iso-string.js","original":{"line":61,"column":23}},{"generated":{"line":67,"column":164},"source":"../node_modules/moment/src/lib/duration/iso-string.js","original":{"line":61,"column":13}},{"generated":{"line":67,"column":167},"source":"../node_modules/moment/src/lib/duration/iso-string.js","original":{"line":61,"column":27}},{"generated":{"line":67,"column":170},"source":"../node_modules/moment/src/lib/duration/iso-string.js","original":{"line":61,"column":9}},{"generated":{"line":67,"column":173},"source":"../node_modules/moment/src/lib/duration/iso-string.js","original":{"line":61,"column":33}},{"generated":{"line":67,"column":175},"source":"../node_modules/moment/src/lib/duration/iso-string.js","original":{"line":56,"column":11}},{"name":"m","generated":{"line":67,"column":180},"source":"../node_modules/moment/src/lib/duration/iso-string.js","original":{"line":62,"column":9}},{"name":"hmsSign","generated":{"line":67,"column":184},"source":"../node_modules/moment/src/lib/duration/iso-string.js","original":{"line":62,"column":13}},{"name":"m","generated":{"line":67,"column":194},"source":"../node_modules/moment/src/lib/duration/iso-string.js","original":{"line":62,"column":23}},{"generated":{"line":67,"column":195},"source":"../node_modules/moment/src/lib/duration/iso-string.js","original":{"line":62,"column":13}},{"generated":{"line":67,"column":198},"source":"../node_modules/moment/src/lib/duration/iso-string.js","original":{"line":62,"column":27}},{"generated":{"line":67,"column":201},"source":"../node_modules/moment/src/lib/duration/iso-string.js","original":{"line":62,"column":9}},{"generated":{"line":67,"column":204},"source":"../node_modules/moment/src/lib/duration/iso-string.js","original":{"line":62,"column":33}},{"generated":{"line":67,"column":206},"source":"../node_modules/moment/src/lib/duration/iso-string.js","original":{"line":56,"column":11}},{"name":"s","generated":{"line":67,"column":211},"source":"../node_modules/moment/src/lib/duration/iso-string.js","original":{"line":63,"column":9}},{"name":"hmsSign","generated":{"line":67,"column":215},"source":"../node_modules/moment/src/lib/duration/iso-string.js","original":{"line":63,"column":13}},{"name":"s","generated":{"line":67,"column":225},"source":"../node_modules/moment/src/lib/duration/iso-string.js","original":{"line":63,"column":23}},{"generated":{"line":67,"column":226},"source":"../node_modules/moment/src/lib/duration/iso-string.js","original":{"line":63,"column":13}},{"generated":{"line":67,"column":229},"source":"../node_modules/moment/src/lib/duration/iso-string.js","original":{"line":63,"column":27}},{"generated":{"line":67,"column":232},"source":"../node_modules/moment/src/lib/duration/iso-string.js","original":{"line":63,"column":9}},{"generated":{"line":67,"column":235},"source":"../node_modules/moment/src/lib/duration/iso-string.js","original":{"line":63,"column":33}},{"generated":{"line":67,"column":237},"source":"../node_modules/moment/src/lib/duration/iso-string.js","original":{"line":56,"column":11}},{"generated":{"line":67,"column":238},"source":"../node_modules/moment/src/lib/duration/iso-string.js","original":{"line":56,"column":4}},{"generated":{"line":68,"column":0},"source":"../node_modules/moment/src/lib/duration/iso-string.js","original":{"line":64,"column":1}}],"sources":{"../node_modules/moment/src/lib/duration/iso-string.js":"import absFloor from '../utils/abs-floor';\nvar abs = Math.abs;\n\nfunction sign(x) {\n    return ((x > 0) - (x < 0)) || +x;\n}\n\nexport function toISOString() {\n    // for ISO strings we do not use the normal bubbling rules:\n    //  * milliseconds bubble up until they become hours\n    //  * days do not bubble at all\n    //  * months bubble up until they become years\n    // This is because there is no context-free conversion between hours and days\n    // (think of clock changes)\n    // and also not between days and months (28-31 days per month)\n    if (!this.isValid()) {\n        return this.localeData().invalidDate();\n    }\n\n    var seconds = abs(this._milliseconds) / 1000;\n    var days         = abs(this._days);\n    var months       = abs(this._months);\n    var minutes, hours, years;\n\n    // 3600 seconds -> 60 minutes -> 1 hour\n    minutes           = absFloor(seconds / 60);\n    hours             = absFloor(minutes / 60);\n    seconds %= 60;\n    minutes %= 60;\n\n    // 12 months -> 1 year\n    years  = absFloor(months / 12);\n    months %= 12;\n\n\n    // inspired by https://github.com/dordille/moment-isoduration/blob/master/moment.isoduration.js\n    var Y = years;\n    var M = months;\n    var D = days;\n    var h = hours;\n    var m = minutes;\n    var s = seconds ? seconds.toFixed(3).replace(/\\.?0+$/, '') : '';\n    var total = this.asSeconds();\n\n    if (!total) {\n        // this is the same as C#'s (Noda) and python (isodate)...\n        // but not other JS (goog.date)\n        return 'P0D';\n    }\n\n    var totalSign = total < 0 ? '-' : '';\n    var ymSign = sign(this._months) !== sign(total) ? '-' : '';\n    var daysSign = sign(this._days) !== sign(total) ? '-' : '';\n    var hmsSign = sign(this._milliseconds) !== sign(total) ? '-' : '';\n\n    return totalSign + 'P' +\n        (Y ? ymSign + Y + 'Y' : '') +\n        (M ? ymSign + M + 'M' : '') +\n        (D ? daysSign + D + 'D' : '') +\n        ((h || m || s) ? 'T' : '') +\n        (h ? hmsSign + h + 'H' : '') +\n        (m ? hmsSign + m + 'M' : '') +\n        (s ? hmsSign + s + 'S' : '');\n}\n"},"lineCount":null}},"hash":"240b2fbb660b82456713653ac5624b97","cacheData":{"env":{}}}